README.rst
setup.py
csgrid2unstr/__init__.py
csgrid2unstr/cubed_sphere.py
csgrid2unstr/main.py
csgrid2unstr/unstr.py
csgrid2unstr.egg-info/PKG-INFO
csgrid2unstr.egg-info/SOURCES.txt
csgrid2unstr.egg-info/dependency_links.txt
csgrid2unstr.egg-info/entry_points.txt
csgrid2unstr.egg-info/requires.txt
csgrid2unstr.egg-info/top_level.txt