Metadata-Version: 1.1
Name: csgrid2unstr
Version: 0.0.1
Summary: Creating and converting cubed-sphere grids to unstructured meshes
Home-page: https://github.com/chiao45/csgrid2unstr
Author: Qiao Chen
Author-email: benechiao@gmail.com
License: MIT
Keywords: Math
Platform: UNKNOWN
Classifier: Programming Language :: Python :: 2.7
Classifier: Programming Language :: Python :: 3.5
Classifier: Programming Language :: Python :: 3.6
Classifier: Topic :: Scientific/Engineering
Classifier: Topic :: Software Development
Classifier: Operating System :: OS Independent
Classifier: Intended Audience :: Science/Research
Classifier: License :: OSI Approved :: MIT License
